README.rst
setup.py
django_kvisits.egg-info/PKG-INFO
django_kvisits.egg-info/SOURCES.txt
django_kvisits.egg-info/dependency_links.txt
django_kvisits.egg-info/requires.txt
django_kvisits.egg-info/top_level.txt
kvisits/__init__.py
kvisits/core.py
kvisits/middleware.py
kvisits/models.py
kvisits/settings.py
kvisits/counterhandlers/__init__.py
kvisits/counterhandlers/counterhandlerbase.py
kvisits/counterhandlers/nocounterhandler.py
kvisits/counterhandlers/dbcounterhandler/__init__.py
kvisits/counterhandlers/dbcounterhandler/models.py
kvisits/hashhandlers/__init__.py
kvisits/hashhandlers/hashhandlerbase.py
kvisits/hashhandlers/headershashhandler.py
kvisits/ignorehandlers/__init__.py
kvisits/ignorehandlers/ignorehandlerbase.py
kvisits/ignorehandlers/noignorehandler.py
kvisits/ignorehandlers/urlignorehandler.py
kvisits/ignorehandlers/useragentignorehandler.py
kvisits/loghandlers/__init__.py
kvisits/loghandlers/loghandlerbase.py
kvisits/loghandlers/nologhandler.py
kvisits/loghandlers/dbloghandler/__init__.py
kvisits/loghandlers/dbloghandler/models.py
kvisits/tests/__init__.py
kvisits/tests/models.py
kvisits/tests/test_counterhandlers.py
kvisits/tests/test_hashhandlers.py
kvisits/tests/test_ignorehandlers.py
kvisits/tests/test_loghandlers.py
kvisits/tests/test_middleware.py
kvisits/tests/test_model.py
kvisits/tests/test_uniqhandlers.py
kvisits/tests/views.py
kvisits/uniqhandlers/__init__.py
kvisits/uniqhandlers/nouniqhandler.py
kvisits/uniqhandlers/uniqhandlerbase.py
kvisits/uniqhandlers/dbuniqhandler/__init__.py
kvisits/uniqhandlers/dbuniqhandler/models.py
testing/__init__.py
testing/settings.py
testing/urls.py