Metadata-Version: 1.1
Name: django-kvisits
Version: 0.0.1
Summary: Visit counter for model objects and urls
Home-page: https://github.com/kaleidos/django-kvisits
Author: Jesús Espino García
Author-email: jespinog@gmail.com
License: BSD
Keywords: django,visit,counter
Platform: UNKNOWN
Classifier: Programming Language :: Python
Classifier: Development Status :: 4 - Beta
Classifier: Framework :: Django
Classifier: Intended Audience :: Developers
Classifier: License :: OSI Approved :: BSD License
Classifier: Operating System :: OS Independent
Classifier: Programming Language :: Python
Classifier: Topic :: Internet :: WWW/HTTP
